rockettp/__init__.py
rockettp/rocket.py
rockettp-1.0.0.dist-info/LICENSE.txt
rockettp-1.0.0.dist-info/METADATA
rockettp-1.0.0.dist-info/WHEEL
rockettp-1.0.0.dist-info/top_level.txt
rockettp-1.0.0.dist-info/RECORD
