Metadata-Version: 2.1
Name: rockettp
Version: 1.0.0
Summary: An awesome package that does something
Home-page: http://pypi.python.org/pypi/rockettp/
Author: Mokadem Adel Abdelkader
Author-email: aa.mokadem@esi-sba.dz
License: LICENSE.txt
License-File: LICENSE.txt
Requires-Dist: rockettp
